{
    "key": "group_613a6799d633a",
    "title": "Alt. Display Author",
    "fields": [
        {
            "key": "field_613a67efc94aa",
            "label": "cmls-alt_author",
            "name": "cmls-post-alt_author",
            "type": "text",
            "instructions": "",
            "required": 0,
            "conditional_logic": 0,
            "wrapper": {
                "width": "",
                "class": "",
                "id": ""
            },
            "default_value": "",
            "placeholder": "",
            "prepend": "",
            "append": "",
            "maxlength": ""
        }
    ],
    "location": [
        [
            {
                "param": "post_type",
                "operator": "==",
                "value": "post"
            }
        ]
    ],
    "menu_order": 0,
    "position": "normal",
    "style": "default",
    "label_placement": "top",
    "instruction_placement": "label",
    "hide_on_screen": "",
    "active": true,
    "description": "Guest author? Enter their name here, and their name will be displayed on this post instead of yours.",
    "modified": 1631217759
}